Astral/__init__.py
Astral/core.py
astral_intelligence-0.1.0.dist-info/licenses/LICENSE
astral_intelligence-0.1.0.dist-info/METADATA
astral_intelligence-0.1.0.dist-info/WHEEL
astral_intelligence-0.1.0.dist-info/top_level.txt
astral_intelligence-0.1.0.dist-info/RECORD
