Metadata-Version: 2.4
Name: astral_intelligence
Version: 0.1.0
Summary: Astral AI Python Library
Author-email: Rith <joar@strombackfamily.com>
License-Expression: MIT
Requires-Python: >=3.8
License-File: LICENSE
Dynamic: license-file
